{
			"type" : "FeatureCollection",
			"features" : [ {
				"type" : "Feature",
				"properties" : {
					"name" : "testnameeee",
					"address" : "testAddress",
					"popupContent" : "testnamewwww"
				},
				"geometry" : {
					"type" : "Point",
					"coordinates" : [ -98.729, 36.4551 ]
				}
			}, {
				"type" : "Feature",
				"properties" : {
					"name" : "testname2",
					"address" : "testAddress2",
					"popupContent" : "testname2"
				},
				"geometry" : {
					"type" : "Point",
					"coordinates" : [ -97.7348, 36.6638 ]
				}
			}, {
				"type" : "Feature",
				"properties" : {
					"name" : "testname3",
					"address" : "testAddress2",
					"popupContent" : "testname3"
				},
				"geometry" : {
					"type" : "Point",
					"coordinates" : [ -92.7348, 36.6638 ]
				}
			} ]
		}